fossl/__init__.py
fossl/__main__.py
fossl/console.py
fossl/github.py
fossl/toml.py
fossl-0.12.0.dist-info/entry_points.txt
fossl-0.12.0.dist-info/LICENSE
fossl-0.12.0.dist-info/WHEEL
fossl-0.12.0.dist-info/METADATA
fossl-0.12.0.dist-info/RECORD
