Metadata-Version: 2.1
Name: fossl
Version: 0.12.0
Summary: Access Free Open Source License information on the command line
Keywords: cli,console,licensing
Author-email: Ralf Luetkemeier <foss@rlue.de>
Requires-Python: >=3.9,<4
Classifier: Development Status :: 4 - Beta
Classifier: Environment :: Console
Classifier: Intended Audience :: Developers
Classifier: License :: OSI Approved :: MIT License
Classifier: Operating System :: MacOS
Classifier: Operating System :: Microsoft :: Windows
Classifier: Operating System :: POSIX :: Linux
Classifier: Programming Language :: Python :: 3
Classifier: Programming Language :: Python :: 3.8
Classifier: Programming Language :: Python :: 3.9
Classifier: Programming Language :: Python :: 3.10
Classifier: Programming Language :: Python :: 3.11
Classifier: Programming Language :: Python :: 3.12
Classifier: Programming Language :: Python :: 3 :: Only
Classifier: Topic :: Software Development
Classifier: Topic :: Utilities
Requires-Dist: cozyconsole >= 0.3.0
Requires-Dist: requests >= 2.27.1
Requires-Dist: rich >=12.0.0
Requires-Dist: rich-argparse-plus >= 0.3.0
Requires-Dist: tomli >= 2.0.0; python_version < '3.11'
Requires-Dist: tomli_w >= 1.0.0
Requires-Dist: flake8 ; extra == "dev"
Requires-Dist: flit ; extra == "dev"
Requires-Dist: pylint ; extra == "dev"
Requires-Dist: pytest ; extra == "dev"
Requires-Dist: pytest-cov ; extra == "dev"
Requires-Dist: tox ; extra == "dev"
Requires-Dist: pytest >=7.2.1 ; extra == "tox"
Provides-Extra: dev
Provides-Extra: tox
